{
    "info": {
      "name": "Questions CRUD",
      "_postman_id": "12345678-aaaa-bbbb-cccc-1234567890ab",
      "description": "Colección para probar CRUD de questions",
      "schema": "https://schema.getpostman.com/json/collection/v2.1.0/collection.json"
    },
    "item": [
      {
        "name": "Get Questions",
        "request": {
          "method": "GET",
          "header": [
            {
              "key": "Authorization",
              "value": "Bearer {{token}}",
              "type": "text"
            }
          ],
          "url": {
            "raw": "http://localhost:3001/questions",
            "protocol": "http",
            "host": ["localhost"],
            "port": "3001",
            "path": ["questions"]
          }
        }
      },
      {
        "name": "Get Questions by Quiz",
        "request": {
          "method": "GET",
          "header": [
            {
              "key": "Authorization",
              "value": "Bearer {{token}}",
              "type": "text"
            }
          ],
          "url": {
            "raw": "http://localhost:3001/questions?id_quiz=1",
            "protocol": "http",
            "host": ["localhost"],
            "port": "3001",
            "path": ["questions"],
            "query": [
              { "key": "id_quiz", "value": "1" }
            ]
          }
        }
      },
      {
        "name": "Create Question",
        "request": {
          "method": "POST",
          "header": [
            {
              "key": "Authorization",
              "value": "Bearer {{token}}",
              "type": "text"
            },
            { "key": "Content-Type", "value": "application/json", "type": "text" }
          ],
          "body": {
            "mode": "raw",
            "raw": "{\n  \"id_quiz\": 1,\n  \"text\": \"¿Qué significa SQL?\",\n  \"type\": \"multiple_choice\",\n  \"options\": [\"Structured Query Language\", \"Simple Query Logic\", \"Secure Quick Language\"],\n  \"answer\": \"Structured Query Language\"\n}"
          },
          "url": {
            "raw": "http://localhost:3001/questions",
            "protocol": "http",
            "host": ["localhost"],
            "port": "3001",
            "path": ["questions"]
          }
        }
      },
      {
        "name": "Update Question",
        "request": {
          "method": "PUT",
          "header": [
            {
              "key": "Authorization",
              "value": "Bearer {{token}}",
              "type": "text"
            },
            { "key": "Content-Type", "value": "application/json", "type": "text" }
          ],
          "body": {
            "mode": "raw",
            "raw": "{\n  \"id_quiz\": 1,\n  \"text\": \"¿Qué significa HTML?\",\n  \"type\": \"multiple_choice\",\n  \"options\": [\"HyperText Markup Language\", \"HighText Machine Language\"],\n  \"answer\": \"HyperText Markup Language\"\n}"
          },
          "url": {
            "raw": "http://localhost:3001/questions/1",
            "protocol": "http",
            "host": ["localhost"],
            "port": "3001",
            "path": ["questions", "1"]
          }
        }
      },
      {
        "name": "Patch Question",
        "request": {
          "method": "PATCH",
          "header": [
            {
              "key": "Authorization",
              "value": "Bearer {{token}}",
              "type": "text"
            },
            { "key": "Content-Type", "value": "application/json", "type": "text" }
          ],
          "body": {
            "mode": "raw",
            "raw": "{\n  \"text\": \"Pregunta corregida solo con patch\"\n}"
          },
          "url": {
            "raw": "http://localhost:3001/questions/1",
            "protocol": "http",
            "host": ["localhost"],
            "port": "3001",
            "path": ["questions", "1"]
          }
        }
      },
      {
        "name": "Delete Question",
        "request": {
          "method": "DELETE",
          "header": [
            {
              "key": "Authorization",
              "value": "Bearer {{token}}",
              "type": "text"
            }
          ],
          "url": {
            "raw": "http://localhost:3001/questions/1",
            "protocol": "http",
            "host": ["localhost"],
            "port": "3001",
            "path": ["questions", "1"]
          }
        }
      }
    ]
  }
  